pytest_async/__init__.py
pytest_async/plugin.py
pytest_async-0.1.1.dist-info/LICENSE
pytest_async-0.1.1.dist-info/WHEEL
pytest_async-0.1.1.dist-info/METADATA
pytest_async-0.1.1.dist-info/RECORD
